{
  "results": {
    "0-0": {
      "match": {
        "code": "242",
        "tournamentCode": 5224,
        "scoreStatus": 0,
        "scoreStatusValue": "Normal",
        "winner": 1,
        "team1": {
          "countryCode": "CHN",
          "countryFlagUrl": "https://img.bwfbadminton.com/image/upload/v2/assets/flag-circle-svg-custom/CHN.png",
          "teamId": null,
          "teamName": null,
          "players": [
            {
              "id": "78837",
              "nameDisplay": "LI Wen Mei",
              "nameType": 1,
              "firstName": "Wen Mei",
              "lastName": "LI",
              "initials": "LW",
              "nameShort": "LI W M ",
              "nameShort2": "LI",
              "slug": "wen-mei-li",
              "countryCode": "CHN",
              "countryName": null,
              "countryFlagUrl": "https://img.bwfbadminton.com/image/upload/v2/assets/flag-circle-svg-custom/CHN.png",
              "avatar": {
                "title": "Wen Mei LI",
                "thumbnailUrl": "https://img.bwfbadminton.com/image/upload/v1590501425/assets/players/thumbnail/78837.jpg"
              }
            },
            {
              "id": "92945",
              "nameDisplay": "WANG Yi Duo",
              "nameType": 1,
              "firstName": "Yi Duo",
              "lastName": "WANG",
              "initials": "WY",
              "nameShort": "WANG Y D ",
              "nameShort2": "WANG",
              "slug": "yi-duo-wang",
              "countryCode": "CHN",
              "countryName": null,
              "countryFlagUrl": "https://img.bwfbadminton.com/image/upload/v2/assets/flag-circle-svg-custom/CHN.png",
              "avatar": {
                "title": "Yi Duo WANG",
                "thumbnailUrl": "https://img.bwfbadminton.com/image/upload/assets/players/thumbnail/profile_female.jpg"
              }
            }
          ],
          "linkName": null
        },
        "team2": {
          "countryCode": null,
          "countryFlagUrl": null,
          "teamId": null,
          "teamName": "Bye",
          "players": [],
          "linkName": "Bye"
        },
        "team1seed": "1",
        "team2seed": null,
        "matchTime": null,
        "matchTimeUtc": null,
        "matchStatus": "F",
        "oopRound": null,
        "oopText": null,
        "oopTypeId": null,
        "eventName": "WD",
        "roundName": "Qual. QF",
        "drawName": "WD - Qualification",
        "courtName": "",
        "courtCode": null,
        "courtIndex": null,
        "locationName": null,
        "duration": null,
        "matchOrder": null,
        "matchTypeId": 4,
        "matchTypeValue": "Women's Doubles",
        "reliability": null,
        "score": [],
        "matches": []
      }
    },
    "0-1": {
      "match": {
        "code": "243",
        "tournamentCode": 5224,
        "scoreStatus": 0,
        "scoreStatusValue": "Normal",
        "winner": 1,
        "team1": {
          "countryCode": "MAS",
          "countryFlagUrl": "https://img.bwfbadminton.com/image/upload/v2/assets/flag-circle-svg-custom/MAS.png",
          "teamId": null,
          "teamName": null,
          "players": [
            {
              "id": "91246",
              "nameDisplay": "HO Lo Ee",
              "nameType": 1,
              "firstName": "Lo Ee",
              "lastName": "HO",
              "initials": "HL",
              "nameShort": "HO L E ",
              "nameShort2": "HO",
              "slug": "lo-ee-ho",
              "countryCode": "MAS",
              "countryName": null,
              "countryFlagUrl": "https://img.bwfbadminton.com/image/upload/v2/assets/flag-circle-svg-custom/MAS.png",
              "avatar": {
                "title": "Lo Ee HO",
                "thumbnailUrl": "https://img.bwfbadminton.com/image/upload/assets/players/thumbnail/profile_female.jpg"
              }
            },
            {
              "id": "76514",
              "nameDisplay": "Amanda YAP",
              "nameType": 0,
              "firstName": "Amanda",
              "lastName": "YAP",
              "initials": "AY",
              "nameShort": "A YAP",
              "nameShort2": "YAP",
              "slug": "amanda-yap",
              "countryCode": "MAS",
              "countryName": null,
              "countryFlagUrl": "https://img.bwfbadminton.com/image/upload/v2/assets/flag-circle-svg-custom/MAS.png",
              "avatar": {
                "title": "Amanda YAP",
                "thumbnailUrl": "https://img.bwfbadminton.com/image/upload/assets/players/thumbnail/profile_female.jpg"
              }
            }
          ],
          "linkName": null
        },
        "team2": {
          "countryCode": "THA",
          "countryFlagUrl": "https://img.bwfbadminton.com/image/upload/v2/assets/flag-circle-svg-custom/THA.png",
          "teamId": null,
          "teamName": null,
          "players": [
            {
              "id": "99375",
              "nameDisplay": "Phattharin AIAMVAREESRISAKUL",
              "nameType": 0,
              "firstName": "Phattharin",
              "lastName": "AIAMVAREESRISAKUL",
              "initials": "PA",
              "nameShort": "P AIAMVAREESRISAKUL",
              "nameShort2": "AIAMVAREESRISAKUL",
              "slug": "phattharin-aiamvareesrisakul",
              "countryCode": "THA",
              "countryName": null,
              "countryFlagUrl": "https://img.bwfbadminton.com/image/upload/v2/assets/flag-circle-svg-custom/THA.png",
              "avatar": {
                "title": "Phattharin AIAMVAREESRISAKUL",
                "thumbnailUrl": "https://img.bwfbadminton.com/image/upload/assets/players/thumbnail/profile_female.jpg"
              }
            },
            {
              "id": "88785",
              "nameDisplay": "Sarisa JANPENG",
              "nameType": 0,
              "firstName": "Sarisa",
              "lastName": "JANPENG",
              "initials": "SJ",
              "nameShort": "S JANPENG",
              "nameShort2": "JANPENG",
              "slug": "sarisa-janpeng",
              "countryCode": "THA",
              "countryName": null,
              "countryFlagUrl": "https://img.bwfbadminton.com/image/upload/v2/assets/flag-circle-svg-custom/THA.png",
              "avatar": {
                "title": "Sarisa JANPENG",
                "thumbnailUrl": "https://img.bwfbadminton.com/image/upload/assets/players/thumbnail/profile_female.jpg"
              }
            }
          ],
          "linkName": null
        },
        "team1seed": null,
        "team2seed": null,
        "matchTime": "2025-05-20 12:30:00",
        "matchTimeUtc": "2025-05-20 04:30:00",
        "matchStatus": "F",
        "oopRound": "4",
        "oopText": "Followed by",
        "oopTypeId": 0,
        "eventName": "WD",
        "roundName": "Qual. QF",
        "drawName": "WD - Qualification",
        "courtName": "Court 3",
        "courtCode": "3",
        "courtIndex": 2,
        "locationName": "Stadium Axiata Arena",
        "duration": 80,
        "matchOrder": null,
        "matchTypeId": 4,
        "matchTypeValue": "Women's Doubles",
        "reliability": 1,
        "score": [
          {
            "set": 1,
            "home": 19,
            "away": 21,
            "lastPointWinner": null,
            "serve": null
          },
          {
            "set": 2,
            "home": 21,
            "away": 14,
            "lastPointWinner": null,
            "serve": null
          },
          {
            "set": 3,
            "home": 22,
            "away": 20,
            "lastPointWinner": null,
            "serve": null
          }
        ],
        "matches": []
      }
    },
    "0-2": {
      "match": {
        "code": "244",
        "tournamentCode": 5224,
        "scoreStatus": 0,
        "scoreStatusValue": "Normal",
        "winner": 2,
        "team1": {
          "countryCode": "MAS",
          "countryFlagUrl": "https://img.bwfbadminton.com/image/upload/v2/assets/flag-circle-svg-custom/MAS.png",
          "teamId": null,
          "teamName": null,
          "players": [
            {
              "id": "50246",
              "nameDisplay": "CHENG Su Hui",
              "nameType": 1,
              "firstName": "Su Hui",
              "lastName": "CHENG",
              "initials": "CS",
              "nameShort": "CHENG S H ",
              "nameShort2": "CHENG",
              "slug": "su-hui-cheng",
              "countryCode": "MAS",
              "countryName": null,
              "countryFlagUrl": "https://img.bwfbadminton.com/image/upload/v2/assets/flag-circle-svg-custom/MAS.png",
              "avatar": {
                "title": "Su Hui CHENG",
                "thumbnailUrl": "https://img.bwfbadminton.com/image/upload/assets/players/thumbnail/profile_female.jpg"
              }
            },
            {
              "id": "87878",
              "nameDisplay": "TAN Zhing Yi",
              "nameType": 1,
              "firstName": "Zhing Yi",
              "lastName": "TAN",
              "initials": "TZ",
              "nameShort": "TAN Z Y ",
              "nameShort2": "TAN",
              "slug": "zhing-yi-tan",
              "countryCode": "MAS",
              "countryName": null,
              "countryFlagUrl": "https://img.bwfbadminton.com/image/upload/v2/assets/flag-circle-svg-custom/MAS.png",
              "avatar": {
                "title": "Zhing Yi TAN",
                "thumbnailUrl": "https://img.bwfbadminton.com/image/upload/assets/players/thumbnail/profile_female.jpg"
              }
            }
          ],
          "linkName": null
        },
        "team2": {
          "countryCode": "TPE",
          "countryFlagUrl": "https://img.bwfbadminton.com/image/upload/v2/assets/flag-circle-svg-custom/TPE.png",
          "teamId": null,
          "teamName": null,
          "players": [
            {
              "id": "80667",
              "nameDisplay": "SUNG Yi-Hsuan",
              "nameType": 1,
              "firstName": "Yi-Hsuan",
              "lastName": "SUNG",
              "initials": "SY",
              "nameShort": "SUNG Y H ",
              "nameShort2": "SUNG",
              "slug": "yi-hsuan-sung",
              "countryCode": "TPE",
              "countryName": null,
              "countryFlagUrl": "https://img.bwfbadminton.com/image/upload/v2/assets/flag-circle-svg-custom/TPE.png",
              "avatar": {
                "title": "Yi-Hsuan SUNG",
                "thumbnailUrl": "https://img.bwfbadminton.com/image/upload/assets/players/thumbnail/profile_female.jpg"
              }
            },
            {
              "id": "60981",
              "nameDisplay": "YANG Yi Hsun",
              "nameType": 1,
              "firstName": "Yi Hsun",
              "lastName": "YANG",
              "initials": "YY",
              "nameShort": "YANG Y H ",
              "nameShort2": "YANG",
              "slug": "yi-hsun-yang",
              "countryCode": "TPE",
              "countryName": null,
              "countryFlagUrl": "https://img.bwfbadminton.com/image/upload/v2/assets/flag-circle-svg-custom/TPE.png",
              "avatar": {
                "title": "Yi Hsun YANG",
                "thumbnailUrl": "https://img.bwfbadminton.com/image/upload/assets/players/thumbnail/profile_female.jpg"
              }
            }
          ],
          "linkName": null
        },
        "team1seed": null,
        "team2seed": null,
        "matchTime": "2025-05-20 12:30:00",
        "matchTimeUtc": "2025-05-20 04:30:00",
        "matchStatus": "F",
        "oopRound": "4",
        "oopText": "Followed by",
        "oopTypeId": 0,
        "eventName": "WD",
        "roundName": "Qual. QF",
        "drawName": "WD - Qualification",
        "courtName": "Court 1",
        "courtCode": "1",
        "courtIndex": 0,
        "locationName": "Stadium Axiata Arena",
        "duration": 61,
        "matchOrder": null,
        "matchTypeId": 4,
        "matchTypeValue": "Women's Doubles",
        "reliability": 1,
        "score": [
          {
            "set": 1,
            "home": 22,
            "away": 20,
            "lastPointWinner": null,
            "serve": null
          },
          {
            "set": 2,
            "home": 13,
            "away": 21,
            "lastPointWinner": null,
            "serve": null
          },
          {
            "set": 3,
            "home": 15,
            "away": 21,
            "lastPointWinner": null,
            "serve": null
          }
        ],
        "matches": []
      }
    },
    "0-3": {
      "match": {
        "code": "245",
        "tournamentCode": 5224,
        "scoreStatus": 0,
        "scoreStatusValue": "Normal",
        "winner": 2,
        "team1": {
          "countryCode": null,
          "countryFlagUrl": null,
          "teamId": null,
          "teamName": "Bye",
          "players": [],
          "linkName": "Bye"
        },
        "team2": {
          "countryCode": "CHN",
          "countryFlagUrl": "https://img.bwfbadminton.com/image/upload/v2/assets/flag-circle-svg-custom/CHN.png",
          "teamId": null,
          "teamName": null,
          "players": [
            {
              "id": "63493",
              "nameDisplay": "KENG Shu Liang",
              "nameType": 1,
              "firstName": "Shu Liang",
              "lastName": "KENG",
              "initials": "KS",
              "nameShort": "KENG S L ",
              "nameShort2": "KENG",
              "slug": "shu-liang-keng",
              "countryCode": "CHN",
              "countryName": null,
              "countryFlagUrl": "https://img.bwfbadminton.com/image/upload/v2/assets/flag-circle-svg-custom/CHN.png",
              "avatar": {
                "title": "Shu Liang KENG",
                "thumbnailUrl": "https://img.bwfbadminton.com/image/upload/assets/players/thumbnail/profile_female.jpg"
              }
            },
            {
              "id": "70109",
              "nameDisplay": "LI Hua Zhou",
              "nameType": 1,
              "firstName": "Hua Zhou",
              "lastName": "LI",
              "initials": "LH",
              "nameShort": "LI H Z ",
              "nameShort2": "LI",
              "slug": "hua-zhou-li",
              "countryCode": "CHN",
              "countryName": null,
              "countryFlagUrl": "https://img.bwfbadminton.com/image/upload/v2/assets/flag-circle-svg-custom/CHN.png",
              "avatar": {
                "title": "Hua Zhou LI",
                "thumbnailUrl": "https://img.bwfbadminton.com/image/upload/assets/players/thumbnail/profile_female.jpg"
              }
            }
          ],
          "linkName": null
        },
        "team1seed": null,
        "team2seed": "2",
        "matchTime": null,
        "matchTimeUtc": null,
        "matchStatus": "F",
        "oopRound": null,
        "oopText": null,
        "oopTypeId": null,
        "eventName": "WD",
        "roundName": "Qual. QF",
        "drawName": "WD - Qualification",
        "courtName": "",
        "courtCode": null,
        "courtIndex": null,
        "locationName": null,
        "duration": null,
        "matchOrder": null,
        "matchTypeId": 4,
        "matchTypeValue": "Women's Doubles",
        "reliability": null,
        "score": [],
        "matches": []
      }
    }
  },
  "matches": [
    {
      "id": 1433953,
      "code": "244",
      "tournamentCode": "294DE888-25E7-4633-A28B-03825F250F61",
      "tournamentName": "PERODUA Malaysia Masters 2025",
      "isTeamMatch": false,
      "scoreStatus": 0,
      "scoreStatusValue": "Normal",
      "winner": 2,
      "team1": {
        "countryCode": "MAS",
        "countryFlagUrl": "https://img.bwfbadminton.com/image/upload/v2/assets/flag-circle-svg-custom/MAS.png",
        "teamId": null,
        "teamName": null,
        "players": [
          {
            "id": "50246",
            "nameDisplay": "CHENG Su Hui",
            "nameType": 1,
            "firstName": "Su Hui",
            "lastName": "CHENG",
            "initials": "CS",
            "nameShort": "CHENG S H ",
            "nameShort2": "CHENG",
            "slug": "su-hui-cheng",
            "countryCode": "MAS",
            "countryName": null,
            "countryFlagUrl": "https://img.bwfbadminton.com/image/upload/v2/assets/flag-circle-svg-custom/MAS.png",
            "avatar": {
              "title": "Su Hui CHENG",
              "thumbnailUrl": "https://img.bwfbadminton.com/image/upload/assets/players/thumbnail/profile_female.jpg"
            }
          },
          {
            "id": "87878",
            "nameDisplay": "TAN Zhing Yi",
            "nameType": 1,
            "firstName": "Zhing Yi",
            "lastName": "TAN",
            "initials": "TZ",
            "nameShort": "TAN Z Y ",
            "nameShort2": "TAN",
            "slug": "zhing-yi-tan",
            "countryCode": "MAS",
            "countryName": null,
            "countryFlagUrl": "https://img.bwfbadminton.com/image/upload/v2/assets/flag-circle-svg-custom/MAS.png",
            "avatar": {
              "title": "Zhing Yi TAN",
              "thumbnailUrl": "https://img.bwfbadminton.com/image/upload/assets/players/thumbnail/profile_female.jpg"
            }
          }
        ],
        "linkName": null
      },
      "team2": {
        "countryCode": "TPE",
        "countryFlagUrl": "https://img.bwfbadminton.com/image/upload/v2/assets/flag-circle-svg-custom/TPE.png",
        "teamId": null,
        "teamName": null,
        "players": [
          {
            "id": "80667",
            "nameDisplay": "SUNG Yi-Hsuan",
            "nameType": 1,
            "firstName": "Yi-Hsuan",
            "lastName": "SUNG",
            "initials": "SY",
            "nameShort": "SUNG Y H ",
            "nameShort2": "SUNG",
            "slug": "yi-hsuan-sung",
            "countryCode": "TPE",
            "countryName": null,
            "countryFlagUrl": "https://img.bwfbadminton.com/image/upload/v2/assets/flag-circle-svg-custom/TPE.png",
            "avatar": {
              "title": "Yi-Hsuan SUNG",
              "thumbnailUrl": "https://img.bwfbadminton.com/image/upload/assets/players/thumbnail/profile_female.jpg"
            }
          },
          {
            "id": "60981",
            "nameDisplay": "YANG Yi Hsun",
            "nameType": 1,
            "firstName": "Yi Hsun",
            "lastName": "YANG",
            "initials": "YY",
            "nameShort": "YANG Y H ",
            "nameShort2": "YANG",
            "slug": "yi-hsun-yang",
            "countryCode": "TPE",
            "countryName": null,
            "countryFlagUrl": "https://img.bwfbadminton.com/image/upload/v2/assets/flag-circle-svg-custom/TPE.png",
            "avatar": {
              "title": "Yi Hsun YANG",
              "thumbnailUrl": "https://img.bwfbadminton.com/image/upload/assets/players/thumbnail/profile_female.jpg"
            }
          }
        ],
        "linkName": null
      },
      "team1seed": null,
      "team2seed": null,
      "matchTime": "2025-05-20 12:30:00",
      "matchTimeUtc": "2025-05-20 04:30:00",
      "matchStatus": "F",
      "matchStatusValue": "Finished",
      "oopRound": "4",
      "oopText": "Followed by",
      "oopTypeId": 0,
      "eventName": "WD",
      "roundName": "Qual. QF",
      "drawName": "WD - Qualification",
      "drawCode": "7",
      "courtName": "Court 1",
      "courtCode": "1",
      "courtIndex": 0,
      "locationName": "Stadium Axiata Arena",
      "duration": 61,
      "time": "01:01",
      "matchOrder": null,
      "matchTypeId": 4,
      "matchTypeValue": "Women's Doubles",
      "matchTypeNo": null,
      "reliability": 1,
      "score": [
        {
          "set": 1,
          "home": 22,
          "away": 20,
          "lastPointWinner": null,
          "serve": null
        },
        {
          "set": 2,
          "home": 13,
          "away": 21,
          "lastPointWinner": null,
          "serve": null
        },
        {
          "set": 3,
          "home": 15,
          "away": 21,
          "lastPointWinner": null,
          "serve": null
        }
      ],
      "matches": []
    },
    {
      "id": 1434038,
      "code": "243",
      "tournamentCode": "294DE888-25E7-4633-A28B-03825F250F61",
      "tournamentName": "PERODUA Malaysia Masters 2025",
      "isTeamMatch": false,
      "scoreStatus": 0,
      "scoreStatusValue": "Normal",
      "winner": 1,
      "team1": {
        "countryCode": "MAS",
        "countryFlagUrl": "https://img.bwfbadminton.com/image/upload/v2/assets/flag-circle-svg-custom/MAS.png",
        "teamId": null,
        "teamName": null,
        "players": [
          {
            "id": "91246",
            "nameDisplay": "HO Lo Ee",
            "nameType": 1,
            "firstName": "Lo Ee",
            "lastName": "HO",
            "initials": "HL",
            "nameShort": "HO L E ",
            "nameShort2": "HO",
            "slug": "lo-ee-ho",
            "countryCode": "MAS",
            "countryName": null,
            "countryFlagUrl": "https://img.bwfbadminton.com/image/upload/v2/assets/flag-circle-svg-custom/MAS.png",
            "avatar": {
              "title": "Lo Ee HO",
              "thumbnailUrl": "https://img.bwfbadminton.com/image/upload/assets/players/thumbnail/profile_female.jpg"
            }
          },
          {
            "id": "76514",
            "nameDisplay": "Amanda YAP",
            "nameType": 0,
            "firstName": "Amanda",
            "lastName": "YAP",
            "initials": "AY",
            "nameShort": "A YAP",
            "nameShort2": "YAP",
            "slug": "amanda-yap",
            "countryCode": "MAS",
            "countryName": null,
            "countryFlagUrl": "https://img.bwfbadminton.com/image/upload/v2/assets/flag-circle-svg-custom/MAS.png",
            "avatar": {
              "title": "Amanda YAP",
              "thumbnailUrl": "https://img.bwfbadminton.com/image/upload/assets/players/thumbnail/profile_female.jpg"
            }
          }
        ],
        "linkName": null
      },
      "team2": {
        "countryCode": "THA",
        "countryFlagUrl": "https://img.bwfbadminton.com/image/upload/v2/assets/flag-circle-svg-custom/THA.png",
        "teamId": null,
        "teamName": null,
        "players": [
          {
            "id": "99375",
            "nameDisplay": "Phattharin AIAMVAREESRISAKUL",
            "nameType": 0,
            "firstName": "Phattharin",
            "lastName": "AIAMVAREESRISAKUL",
            "initials": "PA",
            "nameShort": "P AIAMVAREESRISAKUL",
            "nameShort2": "AIAMVAREESRISAKUL",
            "slug": "phattharin-aiamvareesrisakul",
            "countryCode": "THA",
            "countryName": null,
            "countryFlagUrl": "https://img.bwfbadminton.com/image/upload/v2/assets/flag-circle-svg-custom/THA.png",
            "avatar": {
              "title": "Phattharin AIAMVAREESRISAKUL",
              "thumbnailUrl": "https://img.bwfbadminton.com/image/upload/assets/players/thumbnail/profile_female.jpg"
            }
          },
          {
            "id": "88785",
            "nameDisplay": "Sarisa JANPENG",
            "nameType": 0,
            "firstName": "Sarisa",
            "lastName": "JANPENG",
            "initials": "SJ",
            "nameShort": "S JANPENG",
            "nameShort2": "JANPENG",
            "slug": "sarisa-janpeng",
            "countryCode": "THA",
            "countryName": null,
            "countryFlagUrl": "https://img.bwfbadminton.com/image/upload/v2/assets/flag-circle-svg-custom/THA.png",
            "avatar": {
              "title": "Sarisa JANPENG",
              "thumbnailUrl": "https://img.bwfbadminton.com/image/upload/assets/players/thumbnail/profile_female.jpg"
            }
          }
        ],
        "linkName": null
      },
      "team1seed": null,
      "team2seed": null,
      "matchTime": "2025-05-20 12:30:00",
      "matchTimeUtc": "2025-05-20 04:30:00",
      "matchStatus": "F",
      "matchStatusValue": "Finished",
      "oopRound": "4",
      "oopText": "Followed by",
      "oopTypeId": 0,
      "eventName": "WD",
      "roundName": "Qual. QF",
      "drawName": "WD - Qualification",
      "drawCode": "7",
      "courtName": "Court 3",
      "courtCode": "3",
      "courtIndex": 2,
      "locationName": "Stadium Axiata Arena",
      "duration": 80,
      "time": "01:20",
      "matchOrder": null,
      "matchTypeId": 4,
      "matchTypeValue": "Women's Doubles",
      "matchTypeNo": null,
      "reliability": 1,
      "score": [
        {
          "set": 1,
          "home": 19,
          "away": 21,
          "lastPointWinner": null,
          "serve": null
        },
        {
          "set": 2,
          "home": 21,
          "away": 14,
          "lastPointWinner": null,
          "serve": null
        },
        {
          "set": 3,
          "home": 22,
          "away": 20,
          "lastPointWinner": null,
          "serve": null
        }
      ],
      "matches": []
    },
    {
      "id": 1433888,
      "code": "242",
      "tournamentCode": "294DE888-25E7-4633-A28B-03825F250F61",
      "tournamentName": "PERODUA Malaysia Masters 2025",
      "isTeamMatch": false,
      "scoreStatus": 0,
      "scoreStatusValue": "Normal",
      "winner": 1,
      "team1": {
        "countryCode": "CHN",
        "countryFlagUrl": "https://img.bwfbadminton.com/image/upload/v2/assets/flag-circle-svg-custom/CHN.png",
        "teamId": null,
        "teamName": null,
        "players": [
          {
            "id": "78837",
            "nameDisplay": "LI Wen Mei",
            "nameType": 1,
            "firstName": "Wen Mei",
            "lastName": "LI",
            "initials": "LW",
            "nameShort": "LI W M ",
            "nameShort2": "LI",
            "slug": "wen-mei-li",
            "countryCode": "CHN",
            "countryName": null,
            "countryFlagUrl": "https://img.bwfbadminton.com/image/upload/v2/assets/flag-circle-svg-custom/CHN.png",
            "avatar": {
              "title": "Wen Mei LI",
              "thumbnailUrl": "https://img.bwfbadminton.com/image/upload/v1590501425/assets/players/thumbnail/78837.jpg"
            }
          },
          {
            "id": "92945",
            "nameDisplay": "WANG Yi Duo",
            "nameType": 1,
            "firstName": "Yi Duo",
            "lastName": "WANG",
            "initials": "WY",
            "nameShort": "WANG Y D ",
            "nameShort2": "WANG",
            "slug": "yi-duo-wang",
            "countryCode": "CHN",
            "countryName": null,
            "countryFlagUrl": "https://img.bwfbadminton.com/image/upload/v2/assets/flag-circle-svg-custom/CHN.png",
            "avatar": {
              "title": "Yi Duo WANG",
              "thumbnailUrl": "https://img.bwfbadminton.com/image/upload/assets/players/thumbnail/profile_female.jpg"
            }
          }
        ],
        "linkName": null
      },
      "team2": {
        "countryCode": null,
        "countryFlagUrl": null,
        "teamId": null,
        "teamName": null,
        "players": [],
        "linkName": null
      },
      "team1seed": "1",
      "team2seed": null,
      "matchTime": null,
      "matchTimeUtc": null,
      "matchStatus": "F",
      "matchStatusValue": "Finished",
      "oopRound": null,
      "oopText": null,
      "oopTypeId": null,
      "eventName": "WD",
      "roundName": "Qual. QF",
      "drawName": "WD - Qualification",
      "drawCode": "7",
      "courtName": "",
      "courtCode": null,
      "courtIndex": null,
      "locationName": null,
      "duration": null,
      "time": "00:00",
      "matchOrder": null,
      "matchTypeId": 4,
      "matchTypeValue": "Women's Doubles",
      "matchTypeNo": null,
      "reliability": null,
      "score": [],
      "matches": []
    },
    {
      "id": 1433891,
      "code": "245",
      "tournamentCode": "294DE888-25E7-4633-A28B-03825F250F61",
      "tournamentName": "PERODUA Malaysia Masters 2025",
      "isTeamMatch": false,
      "scoreStatus": 0,
      "scoreStatusValue": "Normal",
      "winner": 2,
      "team1": {
        "countryCode": null,
        "countryFlagUrl": null,
        "teamId": null,
        "teamName": null,
        "players": [],
        "linkName": null
      },
      "team2": {
        "countryCode": "CHN",
        "countryFlagUrl": "https://img.bwfbadminton.com/image/upload/v2/assets/flag-circle-svg-custom/CHN.png",
        "teamId": null,
        "teamName": null,
        "players": [
          {
            "id": "63493",
            "nameDisplay": "KENG Shu Liang",
            "nameType": 1,
            "firstName": "Shu Liang",
            "lastName": "KENG",
            "initials": "KS",
            "nameShort": "KENG S L ",
            "nameShort2": "KENG",
            "slug": "shu-liang-keng",
            "countryCode": "CHN",
            "countryName": null,
            "countryFlagUrl": "https://img.bwfbadminton.com/image/upload/v2/assets/flag-circle-svg-custom/CHN.png",
            "avatar": {
              "title": "Shu Liang KENG",
              "thumbnailUrl": "https://img.bwfbadminton.com/image/upload/assets/players/thumbnail/profile_female.jpg"
            }
          },
          {
            "id": "70109",
            "nameDisplay": "LI Hua Zhou",
            "nameType": 1,
            "firstName": "Hua Zhou",
            "lastName": "LI",
            "initials": "LH",
            "nameShort": "LI H Z ",
            "nameShort2": "LI",
            "slug": "hua-zhou-li",
            "countryCode": "CHN",
            "countryName": null,
            "countryFlagUrl": "https://img.bwfbadminton.com/image/upload/v2/assets/flag-circle-svg-custom/CHN.png",
            "avatar": {
              "title": "Hua Zhou LI",
              "thumbnailUrl": "https://img.bwfbadminton.com/image/upload/assets/players/thumbnail/profile_female.jpg"
            }
          }
        ],
        "linkName": null
      },
      "team1seed": null,
      "team2seed": "2",
      "matchTime": null,
      "matchTimeUtc": null,
      "matchStatus": "F",
      "matchStatusValue": "Finished",
      "oopRound": null,
      "oopText": null,
      "oopTypeId": null,
      "eventName": "WD",
      "roundName": "Qual. QF",
      "drawName": "WD - Qualification",
      "drawCode": "7",
      "courtName": "",
      "courtCode": null,
      "courtIndex": null,
      "locationName": null,
      "duration": null,
      "time": "00:00",
      "matchOrder": null,
      "matchTypeId": 4,
      "matchTypeValue": "Women's Doubles",
      "matchTypeNo": null,
      "reliability": null,
      "score": [],
      "matches": []
    }
  ],
  "drawsize": 4,
  "drawendcol": 4,
  "gameTypeId": 2
}