{
  "results": {
    "0-0": {
      "match": {
        "code": "92",
        "tournamentCode": 4754,
        "scoreStatus": 0,
        "scoreStatusValue": "Normal",
        "winner": 2,
        "team1": {
          "countryCode": "TPE",
          "countryFlagUrl": "https://img.bwfbadminton.com/image/upload/v2/assets/flag-circle-svg-custom/TPE.png",
          "teamId": null,
          "teamName": null,
          "players": [
            {
              "id": "71673",
              "nameDisplay": "CHEN Su Yu",
              "nameType": 1,
              "firstName": "Su Yu",
              "lastName": "CHEN",
              "initials": "CS",
              "nameShort": "CHEN S Y ",
              "nameShort2": "CHEN",
              "slug": "su-yu-chen",
              "countryCode": "TPE",
              "countryName": null,
              "countryFlagUrl": "https://img.bwfbadminton.com/image/upload/v2/assets/flag-circle-svg-custom/TPE.png",
              "avatar": {
                "title": "Su Yu CHEN",
                "thumbnailUrl": "https://img.bwfbadminton.com/image/upload/v1604895492/assets/players/thumbnail/71673.jpg"
              }
            }
          ],
          "linkName": null
        },
        "team2": {
          "countryCode": "TPE",
          "countryFlagUrl": "https://img.bwfbadminton.com/image/upload/v2/assets/flag-circle-svg-custom/TPE.png",
          "teamId": null,
          "teamName": null,
          "players": [
            {
              "id": "96725",
              "nameDisplay": "LIN Hsiang Ti",
              "nameType": 1,
              "firstName": "Hsiang Ti",
              "lastName": "LIN",
              "initials": "LH",
              "nameShort": "LIN H T ",
              "nameShort2": "LIN",
              "slug": "hsiang-ti-lin",
              "countryCode": "TPE",
              "countryName": null,
              "countryFlagUrl": "https://img.bwfbadminton.com/image/upload/v2/assets/flag-circle-svg-custom/TPE.png",
              "avatar": {
                "title": "Hsiang Ti LIN",
                "thumbnailUrl": "https://img.bwfbadminton.com/image/upload/v1689666295/assets/players/thumbnail/96725.jpg"
              }
            }
          ],
          "linkName": null
        },
        "team1seed": null,
        "team2seed": null,
        "matchTime": "2024-08-27 13:15:00",
        "matchTimeUtc": "2024-08-27 04:15:00",
        "matchStatus": "F",
        "oopRound": "3",
        "oopText": "Followed by",
        "oopTypeId": 0,
        "eventName": "WS",
        "roundName": "Qual. QF",
        "drawName": "WS - Qualification",
        "courtName": "Court 3",
        "courtCode": "3",
        "courtIndex": 2,
        "locationName": "Mokpo Indoor Stadium",
        "duration": 55,
        "matchOrder": null,
        "matchTypeId": 2,
        "matchTypeValue": "Women's Singles",
        "reliability": 1,
        "score": [
          {
            "set": 1,
            "home": 21,
            "away": 17,
            "lastPointWinner": null,
            "serve": null
          },
          {
            "set": 2,
            "home": 8,
            "away": 21,
            "lastPointWinner": null,
            "serve": null
          },
          {
            "set": 3,
            "home": 15,
            "away": 21,
            "lastPointWinner": null,
            "serve": null
          }
        ],
        "matches": []
      }
    },
    "0-1": {
      "match": {
        "code": "93",
        "tournamentCode": 4754,
        "scoreStatus": 0,
        "scoreStatusValue": "Normal",
        "winner": 2,
        "team1": {
          "countryCode": "TPE",
          "countryFlagUrl": "https://img.bwfbadminton.com/image/upload/v2/assets/flag-circle-svg-custom/TPE.png",
          "teamId": null,
          "teamName": null,
          "players": [
            {
              "id": "75174",
              "nameDisplay": "LEE Yu-Hsuan",
              "nameType": 1,
              "firstName": "Yu-Hsuan",
              "lastName": "LEE",
              "initials": "LY",
              "nameShort": "LEE Y H ",
              "nameShort2": "LEE",
              "slug": "yu-hsuan-lee",
              "countryCode": "TPE",
              "countryName": null,
              "countryFlagUrl": "https://img.bwfbadminton.com/image/upload/v2/assets/flag-circle-svg-custom/TPE.png",
              "avatar": {
                "title": "Yu-Hsuan LEE",
                "thumbnailUrl": "https://img.bwfbadminton.com/image/upload/assets/players/thumbnail/profile_female.jpg"
              }
            }
          ],
          "linkName": null
        },
        "team2": {
          "countryCode": "KOR",
          "countryFlagUrl": "https://img.bwfbadminton.com/image/upload/v2/assets/flag-circle-svg-custom/KOR.png",
          "teamId": null,
          "teamName": null,
          "players": [
            {
              "id": "73969",
              "nameDisplay": "KIM Ga Ram",
              "nameType": 1,
              "firstName": "Ga Ram",
              "lastName": "KIM",
              "initials": "KG",
              "nameShort": "KIM G R ",
              "nameShort2": "KIM",
              "slug": "ga-ram-kim",
              "countryCode": "KOR",
              "countryName": null,
              "countryFlagUrl": "https://img.bwfbadminton.com/image/upload/v2/assets/flag-circle-svg-custom/KOR.png",
              "avatar": {
                "title": "Ga Ram KIM",
                "thumbnailUrl": "https://img.bwfbadminton.com/image/upload/assets/players/thumbnail/profile_female.jpg"
              }
            }
          ],
          "linkName": null
        },
        "team1seed": null,
        "team2seed": null,
        "matchTime": "2024-08-27 12:35:00",
        "matchTimeUtc": "2024-08-27 03:35:00",
        "matchStatus": "F",
        "oopRound": "2",
        "oopText": "Followed by",
        "oopTypeId": 0,
        "eventName": "WS",
        "roundName": "Qual. QF",
        "drawName": "WS - Qualification",
        "courtName": "Court 3",
        "courtCode": "3",
        "courtIndex": 2,
        "locationName": "Mokpo Indoor Stadium",
        "duration": 35,
        "matchOrder": null,
        "matchTypeId": 2,
        "matchTypeValue": "Women's Singles",
        "reliability": 1,
        "score": [
          {
            "set": 1,
            "home": 12,
            "away": 21,
            "lastPointWinner": null,
            "serve": null
          },
          {
            "set": 2,
            "home": 18,
            "away": 21,
            "lastPointWinner": null,
            "serve": null
          }
        ],
        "matches": []
      }
    },
    "0-2": {
      "match": {
        "code": "94",
        "tournamentCode": 4754,
        "scoreStatus": 0,
        "scoreStatusValue": "Normal",
        "winner": 1,
        "team1": {
          "countryCode": "KOR",
          "countryFlagUrl": "https://img.bwfbadminton.com/image/upload/v2/assets/flag-circle-svg-custom/KOR.png",
          "teamId": null,
          "teamName": null,
          "players": [
            {
              "id": "96038",
              "nameDisplay": "KIM Joo Eun",
              "nameType": 1,
              "firstName": "Joo Eun",
              "lastName": "KIM",
              "initials": "KJ",
              "nameShort": "KIM J E ",
              "nameShort2": "KIM",
              "slug": "joo-eun-kim",
              "countryCode": "KOR",
              "countryName": null,
              "countryFlagUrl": "https://img.bwfbadminton.com/image/upload/v2/assets/flag-circle-svg-custom/KOR.png",
              "avatar": {
                "title": "Joo Eun KIM",
                "thumbnailUrl": "https://img.bwfbadminton.com/image/upload/assets/players/thumbnail/profile_female.jpg"
              }
            }
          ],
          "linkName": null
        },
        "team2": {
          "countryCode": "THA",
          "countryFlagUrl": "https://img.bwfbadminton.com/image/upload/v2/assets/flag-circle-svg-custom/THA.png",
          "teamId": null,
          "teamName": null,
          "players": [
            {
              "id": "69463",
              "nameDisplay": "Pitchamon OPATNIPUTH",
              "nameType": 0,
              "firstName": "Pitchamon",
              "lastName": "OPATNIPUTH",
              "initials": "PO",
              "nameShort": "P OPATNIPUTH",
              "nameShort2": "OPATNIPUTH",
              "slug": "pitchamon-opatniputh",
              "countryCode": "THA",
              "countryName": null,
              "countryFlagUrl": "https://img.bwfbadminton.com/image/upload/v2/assets/flag-circle-svg-custom/THA.png",
              "avatar": {
                "title": "Pitchamon OPATNIPUTH",
                "thumbnailUrl": "https://img.bwfbadminton.com/image/upload/v1689667791/assets/players/thumbnail/69463.jpg"
              }
            }
          ],
          "linkName": null
        },
        "team1seed": null,
        "team2seed": null,
        "matchTime": "2024-08-27 12:35:00",
        "matchTimeUtc": "2024-08-27 03:35:00",
        "matchStatus": "F",
        "oopRound": "2",
        "oopText": "Followed by",
        "oopTypeId": 0,
        "eventName": "WS",
        "roundName": "Qual. QF",
        "drawName": "WS - Qualification",
        "courtName": "Court 1",
        "courtCode": "1",
        "courtIndex": 0,
        "locationName": "Mokpo Indoor Stadium",
        "duration": 82,
        "matchOrder": null,
        "matchTypeId": 2,
        "matchTypeValue": "Women's Singles",
        "reliability": 1,
        "score": [
          {
            "set": 1,
            "home": 23,
            "away": 21,
            "lastPointWinner": null,
            "serve": null
          },
          {
            "set": 2,
            "home": 15,
            "away": 21,
            "lastPointWinner": null,
            "serve": null
          },
          {
            "set": 3,
            "home": 21,
            "away": 18,
            "lastPointWinner": null,
            "serve": null
          }
        ],
        "matches": []
      }
    },
    "0-3": {
      "match": {
        "code": "95",
        "tournamentCode": 4754,
        "scoreStatus": 1,
        "scoreStatusValue": "Walkover",
        "winner": 1,
        "team1": {
          "countryCode": "JPN",
          "countryFlagUrl": "https://img.bwfbadminton.com/image/upload/v2/assets/flag-circle-svg-custom/JPN.png",
          "teamId": null,
          "teamName": null,
          "players": [
            {
              "id": "93372",
              "nameDisplay": "Akari KURIHARA",
              "nameType": 0,
              "firstName": "Akari",
              "lastName": "KURIHARA",
              "initials": "AK",
              "nameShort": "A KURIHARA",
              "nameShort2": "KURIHARA",
              "slug": "akari-kurihara",
              "countryCode": "JPN",
              "countryName": null,
              "countryFlagUrl": "https://img.bwfbadminton.com/image/upload/v2/assets/flag-circle-svg-custom/JPN.png",
              "avatar": {
                "title": "Akari KURIHARA",
                "thumbnailUrl": "https://img.bwfbadminton.com/image/upload/assets/players/thumbnail/profile_female.jpg"
              }
            }
          ],
          "linkName": null
        },
        "team2": {
          "countryCode": "TPE",
          "countryFlagUrl": "https://img.bwfbadminton.com/image/upload/v2/assets/flag-circle-svg-custom/TPE.png",
          "teamId": null,
          "teamName": null,
          "players": [
            {
              "id": "97685",
              "nameDisplay": "HUANG Yu-Hsun",
              "nameType": 1,
              "firstName": "Yu-Hsun",
              "lastName": "HUANG",
              "initials": "HY",
              "nameShort": "HUANG Y H ",
              "nameShort2": "HUANG",
              "slug": "huang-yu-hsun",
              "countryCode": "TPE",
              "countryName": null,
              "countryFlagUrl": "https://img.bwfbadminton.com/image/upload/v2/assets/flag-circle-svg-custom/TPE.png",
              "avatar": {
                "title": "HUANG Yu-Hsun",
                "thumbnailUrl": "https://img.bwfbadminton.com/image/upload/assets/players/thumbnail/profile_female.jpg"
              }
            }
          ],
          "linkName": null
        },
        "team1seed": null,
        "team2seed": "2",
        "matchTime": null,
        "matchTimeUtc": null,
        "matchStatus": "F",
        "oopRound": null,
        "oopText": null,
        "oopTypeId": null,
        "eventName": "WS",
        "roundName": "Qual. QF",
        "drawName": "WS - Qualification",
        "courtName": "",
        "courtCode": null,
        "courtIndex": null,
        "locationName": null,
        "duration": null,
        "matchOrder": null,
        "matchTypeId": 2,
        "matchTypeValue": "Women's Singles",
        "reliability": null,
        "score": [],
        "matches": []
      }
    }
  },
  "matches": [
    {
      "id": 1383335,
      "code": "92",
      "tournamentCode": "79B1D3D3-570E-487F-869D-D4399C90B6F2",
      "tournamentName": "Korea Open 2024",
      "isTeamMatch": false,
      "scoreStatus": 0,
      "scoreStatusValue": "Normal",
      "winner": 2,
      "team1": {
        "countryCode": "TPE",
        "countryFlagUrl": "https://img.bwfbadminton.com/image/upload/v2/assets/flag-circle-svg-custom/TPE.png",
        "teamId": null,
        "teamName": null,
        "players": [
          {
            "id": "71673",
            "nameDisplay": "CHEN Su Yu",
            "nameType": 1,
            "firstName": "Su Yu",
            "lastName": "CHEN",
            "initials": "CS",
            "nameShort": "CHEN S Y ",
            "nameShort2": "CHEN",
            "slug": "su-yu-chen",
            "countryCode": "TPE",
            "countryName": null,
            "countryFlagUrl": "https://img.bwfbadminton.com/image/upload/v2/assets/flag-circle-svg-custom/TPE.png",
            "avatar": {
              "title": "Su Yu CHEN",
              "thumbnailUrl": "https://img.bwfbadminton.com/image/upload/v1604895492/assets/players/thumbnail/71673.jpg"
            }
          }
        ],
        "linkName": null
      },
      "team2": {
        "countryCode": "TPE",
        "countryFlagUrl": "https://img.bwfbadminton.com/image/upload/v2/assets/flag-circle-svg-custom/TPE.png",
        "teamId": null,
        "teamName": null,
        "players": [
          {
            "id": "96725",
            "nameDisplay": "LIN Hsiang Ti",
            "nameType": 1,
            "firstName": "Hsiang Ti",
            "lastName": "LIN",
            "initials": "LH",
            "nameShort": "LIN H T ",
            "nameShort2": "LIN",
            "slug": "hsiang-ti-lin",
            "countryCode": "TPE",
            "countryName": null,
            "countryFlagUrl": "https://img.bwfbadminton.com/image/upload/v2/assets/flag-circle-svg-custom/TPE.png",
            "avatar": {
              "title": "Hsiang Ti LIN",
              "thumbnailUrl": "https://img.bwfbadminton.com/image/upload/v1689666295/assets/players/thumbnail/96725.jpg"
            }
          }
        ],
        "linkName": null
      },
      "team1seed": null,
      "team2seed": null,
      "matchTime": "2024-08-27 13:15:00",
      "matchTimeUtc": "2024-08-27 04:15:00",
      "matchStatus": "F",
      "matchStatusValue": "Finished",
      "oopRound": "3",
      "oopText": "Followed by",
      "oopTypeId": 0,
      "eventName": "WS",
      "roundName": "Qual. QF",
      "drawName": "WS - Qualification",
      "drawCode": "3",
      "courtName": "Court 3",
      "courtCode": "3",
      "courtIndex": 2,
      "locationName": "Mokpo Indoor Stadium",
      "duration": 55,
      "time": "00:55",
      "matchOrder": null,
      "matchTypeId": 2,
      "matchTypeValue": "Women's Singles",
      "matchTypeNo": null,
      "reliability": 1,
      "score": [
        {
          "set": 1,
          "home": 21,
          "away": 17,
          "lastPointWinner": null,
          "serve": null
        },
        {
          "set": 2,
          "home": 8,
          "away": 21,
          "lastPointWinner": null,
          "serve": null
        },
        {
          "set": 3,
          "home": 15,
          "away": 21,
          "lastPointWinner": null,
          "serve": null
        }
      ],
      "matches": []
    },
    {
      "id": 1383310,
      "code": "93",
      "tournamentCode": "79B1D3D3-570E-487F-869D-D4399C90B6F2",
      "tournamentName": "Korea Open 2024",
      "isTeamMatch": false,
      "scoreStatus": 0,
      "scoreStatusValue": "Normal",
      "winner": 2,
      "team1": {
        "countryCode": "TPE",
        "countryFlagUrl": "https://img.bwfbadminton.com/image/upload/v2/assets/flag-circle-svg-custom/TPE.png",
        "teamId": null,
        "teamName": null,
        "players": [
          {
            "id": "75174",
            "nameDisplay": "LEE Yu-Hsuan",
            "nameType": 1,
            "firstName": "Yu-Hsuan",
            "lastName": "LEE",
            "initials": "LY",
            "nameShort": "LEE Y H ",
            "nameShort2": "LEE",
            "slug": "yu-hsuan-lee",
            "countryCode": "TPE",
            "countryName": null,
            "countryFlagUrl": "https://img.bwfbadminton.com/image/upload/v2/assets/flag-circle-svg-custom/TPE.png",
            "avatar": {
              "title": "Yu-Hsuan LEE",
              "thumbnailUrl": "https://img.bwfbadminton.com/image/upload/assets/players/thumbnail/profile_female.jpg"
            }
          }
        ],
        "linkName": null
      },
      "team2": {
        "countryCode": "KOR",
        "countryFlagUrl": "https://img.bwfbadminton.com/image/upload/v2/assets/flag-circle-svg-custom/KOR.png",
        "teamId": null,
        "teamName": null,
        "players": [
          {
            "id": "73969",
            "nameDisplay": "KIM Ga Ram",
            "nameType": 1,
            "firstName": "Ga Ram",
            "lastName": "KIM",
            "initials": "KG",
            "nameShort": "KIM G R ",
            "nameShort2": "KIM",
            "slug": "ga-ram-kim",
            "countryCode": "KOR",
            "countryName": null,
            "countryFlagUrl": "https://img.bwfbadminton.com/image/upload/v2/assets/flag-circle-svg-custom/KOR.png",
            "avatar": {
              "title": "Ga Ram KIM",
              "thumbnailUrl": "https://img.bwfbadminton.com/image/upload/assets/players/thumbnail/profile_female.jpg"
            }
          }
        ],
        "linkName": null
      },
      "team1seed": null,
      "team2seed": null,
      "matchTime": "2024-08-27 12:35:00",
      "matchTimeUtc": "2024-08-27 03:35:00",
      "matchStatus": "F",
      "matchStatusValue": "Finished",
      "oopRound": "2",
      "oopText": "Followed by",
      "oopTypeId": 0,
      "eventName": "WS",
      "roundName": "Qual. QF",
      "drawName": "WS - Qualification",
      "drawCode": "3",
      "courtName": "Court 3",
      "courtCode": "3",
      "courtIndex": 2,
      "locationName": "Mokpo Indoor Stadium",
      "duration": 35,
      "time": "00:35",
      "matchOrder": null,
      "matchTypeId": 2,
      "matchTypeValue": "Women's Singles",
      "matchTypeNo": null,
      "reliability": 1,
      "score": [
        {
          "set": 1,
          "home": 12,
          "away": 21,
          "lastPointWinner": null,
          "serve": null
        },
        {
          "set": 2,
          "home": 18,
          "away": 21,
          "lastPointWinner": null,
          "serve": null
        }
      ],
      "matches": []
    },
    {
      "id": 1383329,
      "code": "94",
      "tournamentCode": "79B1D3D3-570E-487F-869D-D4399C90B6F2",
      "tournamentName": "Korea Open 2024",
      "isTeamMatch": false,
      "scoreStatus": 0,
      "scoreStatusValue": "Normal",
      "winner": 1,
      "team1": {
        "countryCode": "KOR",
        "countryFlagUrl": "https://img.bwfbadminton.com/image/upload/v2/assets/flag-circle-svg-custom/KOR.png",
        "teamId": null,
        "teamName": null,
        "players": [
          {
            "id": "96038",
            "nameDisplay": "KIM Joo Eun",
            "nameType": 1,
            "firstName": "Joo Eun",
            "lastName": "KIM",
            "initials": "KJ",
            "nameShort": "KIM J E ",
            "nameShort2": "KIM",
            "slug": "joo-eun-kim",
            "countryCode": "KOR",
            "countryName": null,
            "countryFlagUrl": "https://img.bwfbadminton.com/image/upload/v2/assets/flag-circle-svg-custom/KOR.png",
            "avatar": {
              "title": "Joo Eun KIM",
              "thumbnailUrl": "https://img.bwfbadminton.com/image/upload/assets/players/thumbnail/profile_female.jpg"
            }
          }
        ],
        "linkName": null
      },
      "team2": {
        "countryCode": "THA",
        "countryFlagUrl": "https://img.bwfbadminton.com/image/upload/v2/assets/flag-circle-svg-custom/THA.png",
        "teamId": null,
        "teamName": null,
        "players": [
          {
            "id": "69463",
            "nameDisplay": "Pitchamon OPATNIPUTH",
            "nameType": 0,
            "firstName": "Pitchamon",
            "lastName": "OPATNIPUTH",
            "initials": "PO",
            "nameShort": "P OPATNIPUTH",
            "nameShort2": "OPATNIPUTH",
            "slug": "pitchamon-opatniputh",
            "countryCode": "THA",
            "countryName": null,
            "countryFlagUrl": "https://img.bwfbadminton.com/image/upload/v2/assets/flag-circle-svg-custom/THA.png",
            "avatar": {
              "title": "Pitchamon OPATNIPUTH",
              "thumbnailUrl": "https://img.bwfbadminton.com/image/upload/v1689667791/assets/players/thumbnail/69463.jpg"
            }
          }
        ],
        "linkName": null
      },
      "team1seed": null,
      "team2seed": null,
      "matchTime": "2024-08-27 12:35:00",
      "matchTimeUtc": "2024-08-27 03:35:00",
      "matchStatus": "F",
      "matchStatusValue": "Finished",
      "oopRound": "2",
      "oopText": "Followed by",
      "oopTypeId": 0,
      "eventName": "WS",
      "roundName": "Qual. QF",
      "drawName": "WS - Qualification",
      "drawCode": "3",
      "courtName": "Court 1",
      "courtCode": "1",
      "courtIndex": 0,
      "locationName": "Mokpo Indoor Stadium",
      "duration": 82,
      "time": "01:22",
      "matchOrder": null,
      "matchTypeId": 2,
      "matchTypeValue": "Women's Singles",
      "matchTypeNo": null,
      "reliability": 1,
      "score": [
        {
          "set": 1,
          "home": 23,
          "away": 21,
          "lastPointWinner": null,
          "serve": null
        },
        {
          "set": 2,
          "home": 15,
          "away": 21,
          "lastPointWinner": null,
          "serve": null
        },
        {
          "set": 3,
          "home": 21,
          "away": 18,
          "lastPointWinner": null,
          "serve": null
        }
      ],
      "matches": []
    },
    {
      "id": 1383321,
      "code": "95",
      "tournamentCode": "79B1D3D3-570E-487F-869D-D4399C90B6F2",
      "tournamentName": "Korea Open 2024",
      "isTeamMatch": false,
      "scoreStatus": 1,
      "scoreStatusValue": "Walkover",
      "winner": 1,
      "team1": {
        "countryCode": "JPN",
        "countryFlagUrl": "https://img.bwfbadminton.com/image/upload/v2/assets/flag-circle-svg-custom/JPN.png",
        "teamId": null,
        "teamName": null,
        "players": [
          {
            "id": "93372",
            "nameDisplay": "Akari KURIHARA",
            "nameType": 0,
            "firstName": "Akari",
            "lastName": "KURIHARA",
            "initials": "AK",
            "nameShort": "A KURIHARA",
            "nameShort2": "KURIHARA",
            "slug": "akari-kurihara",
            "countryCode": "JPN",
            "countryName": null,
            "countryFlagUrl": "https://img.bwfbadminton.com/image/upload/v2/assets/flag-circle-svg-custom/JPN.png",
            "avatar": {
              "title": "Akari KURIHARA",
              "thumbnailUrl": "https://img.bwfbadminton.com/image/upload/assets/players/thumbnail/profile_female.jpg"
            }
          }
        ],
        "linkName": null
      },
      "team2": {
        "countryCode": "TPE",
        "countryFlagUrl": "https://img.bwfbadminton.com/image/upload/v2/assets/flag-circle-svg-custom/TPE.png",
        "teamId": null,
        "teamName": null,
        "players": [
          {
            "id": "97685",
            "nameDisplay": "HUANG Yu-Hsun",
            "nameType": 1,
            "firstName": "Yu-Hsun",
            "lastName": "HUANG",
            "initials": "HY",
            "nameShort": "HUANG Y H ",
            "nameShort2": "HUANG",
            "slug": "huang-yu-hsun",
            "countryCode": "TPE",
            "countryName": null,
            "countryFlagUrl": "https://img.bwfbadminton.com/image/upload/v2/assets/flag-circle-svg-custom/TPE.png",
            "avatar": {
              "title": "HUANG Yu-Hsun",
              "thumbnailUrl": "https://img.bwfbadminton.com/image/upload/assets/players/thumbnail/profile_female.jpg"
            }
          }
        ],
        "linkName": null
      },
      "team1seed": null,
      "team2seed": "2",
      "matchTime": null,
      "matchTimeUtc": null,
      "matchStatus": "F",
      "matchStatusValue": "Finished",
      "oopRound": null,
      "oopText": null,
      "oopTypeId": null,
      "eventName": "WS",
      "roundName": "Qual. QF",
      "drawName": "WS - Qualification",
      "drawCode": "3",
      "courtName": "",
      "courtCode": null,
      "courtIndex": null,
      "locationName": null,
      "duration": null,
      "time": "00:00",
      "matchOrder": null,
      "matchTypeId": 2,
      "matchTypeValue": "Women's Singles",
      "matchTypeNo": null,
      "reliability": null,
      "score": [],
      "matches": []
    }
  ],
  "drawsize": 4,
  "drawendcol": 4,
  "gameTypeId": 1
}