{
  "results": {
    "0-0": {
      "match": {
        "code": "151",
        "tournamentCode": 5256,
        "scoreStatus": 0,
        "scoreStatusValue": "Normal",
        "winner": 1,
        "team1": {
          "countryCode": "DEN",
          "countryFlagUrl": "https://img.bwfbadminton.com/image/upload/v2/assets/flag-circle-svg-custom/DEN.png",
          "teamId": null,
          "teamName": null,
          "players": [
            {
              "id": "91167",
              "nameDisplay": "Rasmus ESPERSEN",
              "nameType": 0,
              "firstName": "Rasmus",
              "lastName": "ESPERSEN",
              "initials": "RE",
              "nameShort": "R ESPERSEN",
              "nameShort2": "ESPERSEN",
              "slug": "rasmus-espersen",
              "countryCode": "DEN",
              "countryName": null,
              "countryFlagUrl": "https://img.bwfbadminton.com/image/upload/v2/assets/flag-circle-svg-custom/DEN.png",
              "avatar": {
                "title": "Rasmus ESPERSEN",
                "thumbnailUrl": "https://img.bwfbadminton.com/image/upload/v1604896571/assets/players/thumbnail/91167.jpg"
              }
            },
            {
              "id": "73857",
              "nameDisplay": "Andreas SØNDERGAARD",
              "nameType": 0,
              "firstName": "Andreas",
              "lastName": "SØNDERGAARD",
              "initials": "AS",
              "nameShort": "A SØNDERGAARD",
              "nameShort2": "SØNDERGAARD",
              "slug": "andreas-sondergaard",
              "countryCode": "DEN",
              "countryName": null,
              "countryFlagUrl": "https://img.bwfbadminton.com/image/upload/v2/assets/flag-circle-svg-custom/DEN.png",
              "avatar": {
                "title": "Andreas SØNDERGAARD",
                "thumbnailUrl": "https://img.bwfbadminton.com/image/upload/assets/players/thumbnail/profile_male.jpg"
              }
            }
          ],
          "linkName": null
        },
        "team2": {
          "countryCode": "ENG",
          "countryFlagUrl": "https://img.bwfbadminton.com/image/upload/v2/assets/flag-circle-svg-custom/ENG.png",
          "teamId": null,
          "teamName": null,
          "players": [
            {
              "id": "49264",
              "nameDisplay": "Ka Him FONG",
              "nameType": 0,
              "firstName": "Ka Him",
              "lastName": "FONG",
              "initials": "KF",
              "nameShort": "K FONG",
              "nameShort2": "FONG",
              "slug": "ka-him-fong",
              "countryCode": "ENG",
              "countryName": null,
              "countryFlagUrl": "https://img.bwfbadminton.com/image/upload/v2/assets/flag-circle-svg-custom/ENG.png",
              "avatar": {
                "title": "Ka Him FONG",
                "thumbnailUrl": "https://img.bwfbadminton.com/image/upload/assets/players/thumbnail/profile_male.jpg"
              }
            },
            {
              "id": "95709",
              "nameDisplay": "Raymond WEBSTER",
              "nameType": 0,
              "firstName": "Raymond",
              "lastName": "WEBSTER",
              "initials": "RW",
              "nameShort": "R WEBSTER",
              "nameShort2": "WEBSTER",
              "slug": "raymond-webster",
              "countryCode": "ENG",
              "countryName": null,
              "countryFlagUrl": "https://img.bwfbadminton.com/image/upload/v2/assets/flag-circle-svg-custom/ENG.png",
              "avatar": {
                "title": "Raymond WEBSTER",
                "thumbnailUrl": "https://img.bwfbadminton.com/image/upload/v1604899189/assets/players/thumbnail/95709.jpg"
              }
            }
          ],
          "linkName": null
        },
        "team1seed": "1",
        "team2seed": null,
        "matchTime": "2025-10-28 10:30:00",
        "matchTimeUtc": "2025-10-28 09:30:00",
        "matchStatus": "F",
        "oopRound": "2",
        "oopText": "Followed by",
        "oopTypeId": 0,
        "eventName": "MD",
        "roundName": "Qual. QF",
        "drawName": "MD - Qualification",
        "courtName": "Court 3",
        "courtCode": "3",
        "courtIndex": 2,
        "locationName": "Saarlandhalle",
        "duration": 17,
        "matchOrder": null,
        "matchTypeId": 3,
        "matchTypeValue": "Men's Doubles",
        "reliability": 1,
        "score": [
          {
            "set": 1,
            "home": 21,
            "away": 1,
            "lastPointWinner": null,
            "serve": null
          },
          {
            "set": 2,
            "home": 21,
            "away": 4,
            "lastPointWinner": null,
            "serve": null
          }
        ],
        "matches": []
      }
    },
    "0-1": {
      "match": {
        "code": "152",
        "tournamentCode": 5256,
        "scoreStatus": 0,
        "scoreStatusValue": "Normal",
        "winner": 2,
        "team1": {
          "countryCode": "NED",
          "countryFlagUrl": "https://img.bwfbadminton.com/image/upload/v2/assets/flag-circle-svg-custom/NED.png",
          "teamId": null,
          "teamName": null,
          "players": [
            {
              "id": "55908",
              "nameDisplay": "Andy BUIJK",
              "nameType": 0,
              "firstName": "Andy",
              "lastName": "BUIJK",
              "initials": "AB",
              "nameShort": "A BUIJK",
              "nameShort2": "BUIJK",
              "slug": "andy-buijk",
              "countryCode": "NED",
              "countryName": null,
              "countryFlagUrl": "https://img.bwfbadminton.com/image/upload/v2/assets/flag-circle-svg-custom/NED.png",
              "avatar": {
                "title": "Andy BUIJK",
                "thumbnailUrl": "https://img.bwfbadminton.com/image/upload/assets/players/thumbnail/profile_male.jpg"
              }
            },
            {
              "id": "65470",
              "nameDisplay": "Brian WASSINK",
              "nameType": 0,
              "firstName": "Brian",
              "lastName": "WASSINK",
              "initials": "BW",
              "nameShort": "B WASSINK",
              "nameShort2": "WASSINK",
              "slug": "brian-wassink",
              "countryCode": "NED",
              "countryName": null,
              "countryFlagUrl": "https://img.bwfbadminton.com/image/upload/v2/assets/flag-circle-svg-custom/NED.png",
              "avatar": {
                "title": "Brian WASSINK",
                "thumbnailUrl": "https://img.bwfbadminton.com/image/upload/assets/players/thumbnail/profile_male.jpg"
              }
            }
          ],
          "linkName": null
        },
        "team2": {
          "countryCode": "GER",
          "countryFlagUrl": "https://img.bwfbadminton.com/image/upload/v2/assets/flag-circle-svg-custom/GER.png",
          "teamId": null,
          "teamName": null,
          "players": [
            {
              "id": "79195",
              "nameDisplay": "Jonathan DRESP",
              "nameType": 0,
              "firstName": "Jonathan",
              "lastName": "DRESP",
              "initials": "JD",
              "nameShort": "J DRESP",
              "nameShort2": "DRESP",
              "slug": "jonathan-dresp",
              "countryCode": "GER",
              "countryName": null,
              "countryFlagUrl": "https://img.bwfbadminton.com/image/upload/v2/assets/flag-circle-svg-custom/GER.png",
              "avatar": {
                "title": "Jonathan DRESP",
                "thumbnailUrl": "https://img.bwfbadminton.com/image/upload/assets/players/thumbnail/profile_male.jpg"
              }
            },
            {
              "id": "91174",
              "nameDisplay": "Simon KRAX",
              "nameType": 0,
              "firstName": "Simon",
              "lastName": "KRAX",
              "initials": "SK",
              "nameShort": "S KRAX",
              "nameShort2": "KRAX",
              "slug": "simon-krax",
              "countryCode": "GER",
              "countryName": null,
              "countryFlagUrl": "https://img.bwfbadminton.com/image/upload/v2/assets/flag-circle-svg-custom/GER.png",
              "avatar": {
                "title": "Simon KRAX",
                "thumbnailUrl": "https://img.bwfbadminton.com/image/upload/assets/players/thumbnail/profile_male.jpg"
              }
            }
          ],
          "linkName": null
        },
        "team1seed": null,
        "team2seed": null,
        "matchTime": "2025-10-28 09:30:00",
        "matchTimeUtc": "2025-10-28 08:30:00",
        "matchStatus": "F",
        "oopRound": "1",
        "oopText": "Starting at 9:30 AM",
        "oopTypeId": 1,
        "eventName": "MD",
        "roundName": "Qual. QF",
        "drawName": "MD - Qualification",
        "courtName": "Court 1",
        "courtCode": "1",
        "courtIndex": 0,
        "locationName": "Saarlandhalle",
        "duration": 55,
        "matchOrder": null,
        "matchTypeId": 3,
        "matchTypeValue": "Men's Doubles",
        "reliability": 0,
        "score": [
          {
            "set": 1,
            "home": 21,
            "away": 19,
            "lastPointWinner": null,
            "serve": null
          },
          {
            "set": 2,
            "home": 11,
            "away": 21,
            "lastPointWinner": null,
            "serve": null
          },
          {
            "set": 3,
            "home": 19,
            "away": 21,
            "lastPointWinner": null,
            "serve": null
          }
        ],
        "matches": []
      }
    },
    "0-2": {
      "match": {
        "code": "153",
        "tournamentCode": 5256,
        "scoreStatus": 0,
        "scoreStatusValue": "Normal",
        "winner": 1,
        "team1": {
          "countryCode": "SUI",
          "countryFlagUrl": "https://img.bwfbadminton.com/image/upload/v2/assets/flag-circle-svg-custom/SUI.png",
          "teamId": null,
          "teamName": null,
          "players": [
            {
              "id": "97214",
              "nameDisplay": "Yann ORTEU",
              "nameType": 0,
              "firstName": "Yann",
              "lastName": "ORTEU",
              "initials": "YO",
              "nameShort": "Y ORTEU",
              "nameShort2": "ORTEU",
              "slug": "yann-orteu",
              "countryCode": "SUI",
              "countryName": null,
              "countryFlagUrl": "https://img.bwfbadminton.com/image/upload/v2/assets/flag-circle-svg-custom/SUI.png",
              "avatar": {
                "title": "Yann ORTEU",
                "thumbnailUrl": "https://img.bwfbadminton.com/image/upload/assets/players/thumbnail/profile_male.jpg"
              }
            },
            {
              "id": "91987",
              "nameDisplay": "Minh Quang PHAM",
              "nameType": 0,
              "firstName": "Minh Quang",
              "lastName": "PHAM",
              "initials": "MP",
              "nameShort": "M PHAM",
              "nameShort2": "PHAM",
              "slug": "minh-quang-pham",
              "countryCode": "SUI",
              "countryName": null,
              "countryFlagUrl": "https://img.bwfbadminton.com/image/upload/v2/assets/flag-circle-svg-custom/SUI.png",
              "avatar": {
                "title": "Minh Quang PHAM",
                "thumbnailUrl": "https://img.bwfbadminton.com/image/upload/v1741930562/assets/players/thumbnail/91987.jpg"
              }
            }
          ],
          "linkName": null
        },
        "team2": {
          "countryCode": "ESP",
          "countryFlagUrl": "https://img.bwfbadminton.com/image/upload/v2/assets/flag-circle-svg-custom/ESP.png",
          "teamId": null,
          "teamName": null,
          "players": [
            {
              "id": "97537",
              "nameDisplay": "Adolfo LOPEZ",
              "nameType": 0,
              "firstName": "Adolfo",
              "lastName": "LOPEZ",
              "initials": "AL",
              "nameShort": "A LOPEZ",
              "nameShort2": "LOPEZ",
              "slug": "adolfo-lopez",
              "countryCode": "ESP",
              "countryName": null,
              "countryFlagUrl": "https://img.bwfbadminton.com/image/upload/v2/assets/flag-circle-svg-custom/ESP.png",
              "avatar": {
                "title": "Adolfo LOPEZ",
                "thumbnailUrl": "https://img.bwfbadminton.com/image/upload/assets/players/thumbnail/profile_male.jpg"
              }
            },
            {
              "id": "72549",
              "nameDisplay": "Rodrigo SANJURJO",
              "nameType": 0,
              "firstName": "Rodrigo",
              "lastName": "SANJURJO",
              "initials": "RS",
              "nameShort": "R SANJURJO",
              "nameShort2": "SANJURJO",
              "slug": "rodrigo-sanjurjo",
              "countryCode": "ESP",
              "countryName": null,
              "countryFlagUrl": "https://img.bwfbadminton.com/image/upload/v2/assets/flag-circle-svg-custom/ESP.png",
              "avatar": {
                "title": "Rodrigo SANJURJO",
                "thumbnailUrl": "https://img.bwfbadminton.com/image/upload/assets/players/thumbnail/profile_male.jpg"
              }
            }
          ],
          "linkName": null
        },
        "team1seed": null,
        "team2seed": null,
        "matchTime": "2025-10-28 09:40:00",
        "matchTimeUtc": "2025-10-28 08:40:00",
        "matchStatus": "F",
        "oopRound": "1",
        "oopText": "Starting at 9:40 AM",
        "oopTypeId": 1,
        "eventName": "MD",
        "roundName": "Qual. QF",
        "drawName": "MD - Qualification",
        "courtName": "Court 3",
        "courtCode": "3",
        "courtIndex": 2,
        "locationName": "Saarlandhalle",
        "duration": 35,
        "matchOrder": null,
        "matchTypeId": 3,
        "matchTypeValue": "Men's Doubles",
        "reliability": 0,
        "score": [
          {
            "set": 1,
            "home": 21,
            "away": 16,
            "lastPointWinner": null,
            "serve": null
          },
          {
            "set": 2,
            "home": 21,
            "away": 14,
            "lastPointWinner": null,
            "serve": null
          }
        ],
        "matches": []
      }
    },
    "0-3": {
      "match": {
        "code": "154",
        "tournamentCode": 5256,
        "scoreStatus": 0,
        "scoreStatusValue": "Normal",
        "winner": 1,
        "team1": {
          "countryCode": "ESP",
          "countryFlagUrl": "https://img.bwfbadminton.com/image/upload/v2/assets/flag-circle-svg-custom/ESP.png",
          "teamId": null,
          "teamName": null,
          "players": [
            {
              "id": "64646",
              "nameDisplay": "Jacobo FERNANDEZ",
              "nameType": 0,
              "firstName": "Jacobo",
              "lastName": "FERNANDEZ",
              "initials": "JF",
              "nameShort": "J FERNANDEZ",
              "nameShort2": "FERNANDEZ",
              "slug": "jacobo-fernandez",
              "countryCode": "ESP",
              "countryName": null,
              "countryFlagUrl": "https://img.bwfbadminton.com/image/upload/v2/assets/flag-circle-svg-custom/ESP.png",
              "avatar": {
                "title": "Jacobo FERNANDEZ",
                "thumbnailUrl": "https://img.bwfbadminton.com/image/upload/assets/players/thumbnail/profile_male.jpg"
              }
            },
            {
              "id": "61331",
              "nameDisplay": "Alberto PERALS",
              "nameType": 0,
              "firstName": "Alberto",
              "lastName": "PERALS",
              "initials": "AP",
              "nameShort": "A PERALS",
              "nameShort2": "PERALS",
              "slug": "alberto-perals",
              "countryCode": "ESP",
              "countryName": null,
              "countryFlagUrl": "https://img.bwfbadminton.com/image/upload/v2/assets/flag-circle-svg-custom/ESP.png",
              "avatar": {
                "title": "Alberto PERALS",
                "thumbnailUrl": "https://img.bwfbadminton.com/image/upload/assets/players/thumbnail/profile_male.jpg"
              }
            }
          ],
          "linkName": null
        },
        "team2": {
          "countryCode": "IRL",
          "countryFlagUrl": "https://img.bwfbadminton.com/image/upload/v2/assets/flag-circle-svg-custom/IRL.png",
          "teamId": null,
          "teamName": null,
          "players": [
            {
              "id": "63756",
              "nameDisplay": "Scott GUILDEA",
              "nameType": 0,
              "firstName": "Scott",
              "lastName": "GUILDEA",
              "initials": "SG",
              "nameShort": "S GUILDEA",
              "nameShort2": "GUILDEA",
              "slug": "scott-guildea",
              "countryCode": "IRL",
              "countryName": null,
              "countryFlagUrl": "https://img.bwfbadminton.com/image/upload/v2/assets/flag-circle-svg-custom/IRL.png",
              "avatar": {
                "title": "Scott GUILDEA",
                "thumbnailUrl": "https://img.bwfbadminton.com/image/upload/assets/players/thumbnail/profile_male.jpg"
              }
            },
            {
              "id": "92985",
              "nameDisplay": "Paul REYNOLDS",
              "nameType": 0,
              "firstName": "Paul",
              "lastName": "REYNOLDS",
              "initials": "PR",
              "nameShort": "P REYNOLDS",
              "nameShort2": "REYNOLDS",
              "slug": "paul-reynolds",
              "countryCode": "IRL",
              "countryName": null,
              "countryFlagUrl": "https://img.bwfbadminton.com/image/upload/v2/assets/flag-circle-svg-custom/IRL.png",
              "avatar": {
                "title": "Paul REYNOLDS",
                "thumbnailUrl": "https://img.bwfbadminton.com/image/upload/v1604899249/assets/players/thumbnail/92985.jpg"
              }
            }
          ],
          "linkName": null
        },
        "team1seed": null,
        "team2seed": "2",
        "matchTime": "2025-10-28 10:25:00",
        "matchTimeUtc": "2025-10-28 09:25:00",
        "matchStatus": "F",
        "oopRound": "2",
        "oopText": "Followed by",
        "oopTypeId": 0,
        "eventName": "MD",
        "roundName": "Qual. QF",
        "drawName": "MD - Qualification",
        "courtName": "Court 2",
        "courtCode": "2",
        "courtIndex": 1,
        "locationName": "Saarlandhalle",
        "duration": 31,
        "matchOrder": null,
        "matchTypeId": 3,
        "matchTypeValue": "Men's Doubles",
        "reliability": 1,
        "score": [
          {
            "set": 1,
            "home": 21,
            "away": 14,
            "lastPointWinner": null,
            "serve": null
          },
          {
            "set": 2,
            "home": 21,
            "away": 18,
            "lastPointWinner": null,
            "serve": null
          }
        ],
        "matches": []
      }
    }
  },
  "matches": [
    {
      "id": 1480876,
      "code": "151",
      "tournamentCode": "F208B31A-8008-4D28-8D6B-84328C948A5F",
      "tournamentName": "HYLO Open 2025",
      "isTeamMatch": false,
      "scoreStatus": 0,
      "scoreStatusValue": "Normal",
      "winner": 1,
      "team1": {
        "countryCode": "DEN",
        "countryFlagUrl": "https://img.bwfbadminton.com/image/upload/v2/assets/flag-circle-svg-custom/DEN.png",
        "teamId": null,
        "teamName": null,
        "players": [
          {
            "id": "91167",
            "nameDisplay": "Rasmus ESPERSEN",
            "nameType": 0,
            "firstName": "Rasmus",
            "lastName": "ESPERSEN",
            "initials": "RE",
            "nameShort": "R ESPERSEN",
            "nameShort2": "ESPERSEN",
            "slug": "rasmus-espersen",
            "countryCode": "DEN",
            "countryName": null,
            "countryFlagUrl": "https://img.bwfbadminton.com/image/upload/v2/assets/flag-circle-svg-custom/DEN.png",
            "avatar": {
              "title": "Rasmus ESPERSEN",
              "thumbnailUrl": "https://img.bwfbadminton.com/image/upload/v1604896571/assets/players/thumbnail/91167.jpg"
            }
          },
          {
            "id": "73857",
            "nameDisplay": "Andreas SØNDERGAARD",
            "nameType": 0,
            "firstName": "Andreas",
            "lastName": "SØNDERGAARD",
            "initials": "AS",
            "nameShort": "A SØNDERGAARD",
            "nameShort2": "SØNDERGAARD",
            "slug": "andreas-sondergaard",
            "countryCode": "DEN",
            "countryName": null,
            "countryFlagUrl": "https://img.bwfbadminton.com/image/upload/v2/assets/flag-circle-svg-custom/DEN.png",
            "avatar": {
              "title": "Andreas SØNDERGAARD",
              "thumbnailUrl": "https://img.bwfbadminton.com/image/upload/assets/players/thumbnail/profile_male.jpg"
            }
          }
        ],
        "linkName": null
      },
      "team2": {
        "countryCode": "ENG",
        "countryFlagUrl": "https://img.bwfbadminton.com/image/upload/v2/assets/flag-circle-svg-custom/ENG.png",
        "teamId": null,
        "teamName": null,
        "players": [
          {
            "id": "49264",
            "nameDisplay": "Ka Him FONG",
            "nameType": 0,
            "firstName": "Ka Him",
            "lastName": "FONG",
            "initials": "KF",
            "nameShort": "K FONG",
            "nameShort2": "FONG",
            "slug": "ka-him-fong",
            "countryCode": "ENG",
            "countryName": null,
            "countryFlagUrl": "https://img.bwfbadminton.com/image/upload/v2/assets/flag-circle-svg-custom/ENG.png",
            "avatar": {
              "title": "Ka Him FONG",
              "thumbnailUrl": "https://img.bwfbadminton.com/image/upload/assets/players/thumbnail/profile_male.jpg"
            }
          },
          {
            "id": "95709",
            "nameDisplay": "Raymond WEBSTER",
            "nameType": 0,
            "firstName": "Raymond",
            "lastName": "WEBSTER",
            "initials": "RW",
            "nameShort": "R WEBSTER",
            "nameShort2": "WEBSTER",
            "slug": "raymond-webster",
            "countryCode": "ENG",
            "countryName": null,
            "countryFlagUrl": "https://img.bwfbadminton.com/image/upload/v2/assets/flag-circle-svg-custom/ENG.png",
            "avatar": {
              "title": "Raymond WEBSTER",
              "thumbnailUrl": "https://img.bwfbadminton.com/image/upload/v1604899189/assets/players/thumbnail/95709.jpg"
            }
          }
        ],
        "linkName": null
      },
      "team1seed": "1",
      "team2seed": null,
      "matchTime": "2025-10-28 10:30:00",
      "matchTimeUtc": "2025-10-28 09:30:00",
      "matchStatus": "F",
      "matchStatusValue": "Finished",
      "oopRound": "2",
      "oopText": "Followed by",
      "oopTypeId": 0,
      "eventName": "MD",
      "roundName": "Qual. QF",
      "drawName": "MD - Qualification",
      "drawCode": "5",
      "courtName": "Court 3",
      "courtCode": "3",
      "courtIndex": 2,
      "locationName": "Saarlandhalle",
      "duration": 17,
      "time": "00:17",
      "matchOrder": null,
      "matchTypeId": 3,
      "matchTypeValue": "Men's Doubles",
      "matchTypeNo": null,
      "reliability": 1,
      "score": [
        {
          "set": 1,
          "home": 21,
          "away": 1,
          "lastPointWinner": null,
          "serve": null
        },
        {
          "set": 2,
          "home": 21,
          "away": 4,
          "lastPointWinner": null,
          "serve": null
        }
      ],
      "matches": []
    },
    {
      "id": 1480877,
      "code": "152",
      "tournamentCode": "F208B31A-8008-4D28-8D6B-84328C948A5F",
      "tournamentName": "HYLO Open 2025",
      "isTeamMatch": false,
      "scoreStatus": 0,
      "scoreStatusValue": "Normal",
      "winner": 2,
      "team1": {
        "countryCode": "NED",
        "countryFlagUrl": "https://img.bwfbadminton.com/image/upload/v2/assets/flag-circle-svg-custom/NED.png",
        "teamId": null,
        "teamName": null,
        "players": [
          {
            "id": "55908",
            "nameDisplay": "Andy BUIJK",
            "nameType": 0,
            "firstName": "Andy",
            "lastName": "BUIJK",
            "initials": "AB",
            "nameShort": "A BUIJK",
            "nameShort2": "BUIJK",
            "slug": "andy-buijk",
            "countryCode": "NED",
            "countryName": null,
            "countryFlagUrl": "https://img.bwfbadminton.com/image/upload/v2/assets/flag-circle-svg-custom/NED.png",
            "avatar": {
              "title": "Andy BUIJK",
              "thumbnailUrl": "https://img.bwfbadminton.com/image/upload/assets/players/thumbnail/profile_male.jpg"
            }
          },
          {
            "id": "65470",
            "nameDisplay": "Brian WASSINK",
            "nameType": 0,
            "firstName": "Brian",
            "lastName": "WASSINK",
            "initials": "BW",
            "nameShort": "B WASSINK",
            "nameShort2": "WASSINK",
            "slug": "brian-wassink",
            "countryCode": "NED",
            "countryName": null,
            "countryFlagUrl": "https://img.bwfbadminton.com/image/upload/v2/assets/flag-circle-svg-custom/NED.png",
            "avatar": {
              "title": "Brian WASSINK",
              "thumbnailUrl": "https://img.bwfbadminton.com/image/upload/assets/players/thumbnail/profile_male.jpg"
            }
          }
        ],
        "linkName": null
      },
      "team2": {
        "countryCode": "GER",
        "countryFlagUrl": "https://img.bwfbadminton.com/image/upload/v2/assets/flag-circle-svg-custom/GER.png",
        "teamId": null,
        "teamName": null,
        "players": [
          {
            "id": "79195",
            "nameDisplay": "Jonathan DRESP",
            "nameType": 0,
            "firstName": "Jonathan",
            "lastName": "DRESP",
            "initials": "JD",
            "nameShort": "J DRESP",
            "nameShort2": "DRESP",
            "slug": "jonathan-dresp",
            "countryCode": "GER",
            "countryName": null,
            "countryFlagUrl": "https://img.bwfbadminton.com/image/upload/v2/assets/flag-circle-svg-custom/GER.png",
            "avatar": {
              "title": "Jonathan DRESP",
              "thumbnailUrl": "https://img.bwfbadminton.com/image/upload/assets/players/thumbnail/profile_male.jpg"
            }
          },
          {
            "id": "91174",
            "nameDisplay": "Simon KRAX",
            "nameType": 0,
            "firstName": "Simon",
            "lastName": "KRAX",
            "initials": "SK",
            "nameShort": "S KRAX",
            "nameShort2": "KRAX",
            "slug": "simon-krax",
            "countryCode": "GER",
            "countryName": null,
            "countryFlagUrl": "https://img.bwfbadminton.com/image/upload/v2/assets/flag-circle-svg-custom/GER.png",
            "avatar": {
              "title": "Simon KRAX",
              "thumbnailUrl": "https://img.bwfbadminton.com/image/upload/assets/players/thumbnail/profile_male.jpg"
            }
          }
        ],
        "linkName": null
      },
      "team1seed": null,
      "team2seed": null,
      "matchTime": "2025-10-28 09:30:00",
      "matchTimeUtc": "2025-10-28 08:30:00",
      "matchStatus": "F",
      "matchStatusValue": "Finished",
      "oopRound": "1",
      "oopText": "Starting at 9:30 AM",
      "oopTypeId": 1,
      "eventName": "MD",
      "roundName": "Qual. QF",
      "drawName": "MD - Qualification",
      "drawCode": "5",
      "courtName": "Court 1",
      "courtCode": "1",
      "courtIndex": 0,
      "locationName": "Saarlandhalle",
      "duration": 55,
      "time": "00:55",
      "matchOrder": null,
      "matchTypeId": 3,
      "matchTypeValue": "Men's Doubles",
      "matchTypeNo": null,
      "reliability": 0,
      "score": [
        {
          "set": 1,
          "home": 21,
          "away": 19,
          "lastPointWinner": null,
          "serve": null
        },
        {
          "set": 2,
          "home": 11,
          "away": 21,
          "lastPointWinner": null,
          "serve": null
        },
        {
          "set": 3,
          "home": 19,
          "away": 21,
          "lastPointWinner": null,
          "serve": null
        }
      ],
      "matches": []
    },
    {
      "id": 1480878,
      "code": "153",
      "tournamentCode": "F208B31A-8008-4D28-8D6B-84328C948A5F",
      "tournamentName": "HYLO Open 2025",
      "isTeamMatch": false,
      "scoreStatus": 0,
      "scoreStatusValue": "Normal",
      "winner": 1,
      "team1": {
        "countryCode": "SUI",
        "countryFlagUrl": "https://img.bwfbadminton.com/image/upload/v2/assets/flag-circle-svg-custom/SUI.png",
        "teamId": null,
        "teamName": null,
        "players": [
          {
            "id": "97214",
            "nameDisplay": "Yann ORTEU",
            "nameType": 0,
            "firstName": "Yann",
            "lastName": "ORTEU",
            "initials": "YO",
            "nameShort": "Y ORTEU",
            "nameShort2": "ORTEU",
            "slug": "yann-orteu",
            "countryCode": "SUI",
            "countryName": null,
            "countryFlagUrl": "https://img.bwfbadminton.com/image/upload/v2/assets/flag-circle-svg-custom/SUI.png",
            "avatar": {
              "title": "Yann ORTEU",
              "thumbnailUrl": "https://img.bwfbadminton.com/image/upload/assets/players/thumbnail/profile_male.jpg"
            }
          },
          {
            "id": "91987",
            "nameDisplay": "Minh Quang PHAM",
            "nameType": 0,
            "firstName": "Minh Quang",
            "lastName": "PHAM",
            "initials": "MP",
            "nameShort": "M PHAM",
            "nameShort2": "PHAM",
            "slug": "minh-quang-pham",
            "countryCode": "SUI",
            "countryName": null,
            "countryFlagUrl": "https://img.bwfbadminton.com/image/upload/v2/assets/flag-circle-svg-custom/SUI.png",
            "avatar": {
              "title": "Minh Quang PHAM",
              "thumbnailUrl": "https://img.bwfbadminton.com/image/upload/v1741930562/assets/players/thumbnail/91987.jpg"
            }
          }
        ],
        "linkName": null
      },
      "team2": {
        "countryCode": "ESP",
        "countryFlagUrl": "https://img.bwfbadminton.com/image/upload/v2/assets/flag-circle-svg-custom/ESP.png",
        "teamId": null,
        "teamName": null,
        "players": [
          {
            "id": "97537",
            "nameDisplay": "Adolfo LOPEZ",
            "nameType": 0,
            "firstName": "Adolfo",
            "lastName": "LOPEZ",
            "initials": "AL",
            "nameShort": "A LOPEZ",
            "nameShort2": "LOPEZ",
            "slug": "adolfo-lopez",
            "countryCode": "ESP",
            "countryName": null,
            "countryFlagUrl": "https://img.bwfbadminton.com/image/upload/v2/assets/flag-circle-svg-custom/ESP.png",
            "avatar": {
              "title": "Adolfo LOPEZ",
              "thumbnailUrl": "https://img.bwfbadminton.com/image/upload/assets/players/thumbnail/profile_male.jpg"
            }
          },
          {
            "id": "72549",
            "nameDisplay": "Rodrigo SANJURJO",
            "nameType": 0,
            "firstName": "Rodrigo",
            "lastName": "SANJURJO",
            "initials": "RS",
            "nameShort": "R SANJURJO",
            "nameShort2": "SANJURJO",
            "slug": "rodrigo-sanjurjo",
            "countryCode": "ESP",
            "countryName": null,
            "countryFlagUrl": "https://img.bwfbadminton.com/image/upload/v2/assets/flag-circle-svg-custom/ESP.png",
            "avatar": {
              "title": "Rodrigo SANJURJO",
              "thumbnailUrl": "https://img.bwfbadminton.com/image/upload/assets/players/thumbnail/profile_male.jpg"
            }
          }
        ],
        "linkName": null
      },
      "team1seed": null,
      "team2seed": null,
      "matchTime": "2025-10-28 09:40:00",
      "matchTimeUtc": "2025-10-28 08:40:00",
      "matchStatus": "F",
      "matchStatusValue": "Finished",
      "oopRound": "1",
      "oopText": "Starting at 9:40 AM",
      "oopTypeId": 1,
      "eventName": "MD",
      "roundName": "Qual. QF",
      "drawName": "MD - Qualification",
      "drawCode": "5",
      "courtName": "Court 3",
      "courtCode": "3",
      "courtIndex": 2,
      "locationName": "Saarlandhalle",
      "duration": 35,
      "time": "00:35",
      "matchOrder": null,
      "matchTypeId": 3,
      "matchTypeValue": "Men's Doubles",
      "matchTypeNo": null,
      "reliability": 0,
      "score": [
        {
          "set": 1,
          "home": 21,
          "away": 16,
          "lastPointWinner": null,
          "serve": null
        },
        {
          "set": 2,
          "home": 21,
          "away": 14,
          "lastPointWinner": null,
          "serve": null
        }
      ],
      "matches": []
    },
    {
      "id": 1480879,
      "code": "154",
      "tournamentCode": "F208B31A-8008-4D28-8D6B-84328C948A5F",
      "tournamentName": "HYLO Open 2025",
      "isTeamMatch": false,
      "scoreStatus": 0,
      "scoreStatusValue": "Normal",
      "winner": 1,
      "team1": {
        "countryCode": "ESP",
        "countryFlagUrl": "https://img.bwfbadminton.com/image/upload/v2/assets/flag-circle-svg-custom/ESP.png",
        "teamId": null,
        "teamName": null,
        "players": [
          {
            "id": "64646",
            "nameDisplay": "Jacobo FERNANDEZ",
            "nameType": 0,
            "firstName": "Jacobo",
            "lastName": "FERNANDEZ",
            "initials": "JF",
            "nameShort": "J FERNANDEZ",
            "nameShort2": "FERNANDEZ",
            "slug": "jacobo-fernandez",
            "countryCode": "ESP",
            "countryName": null,
            "countryFlagUrl": "https://img.bwfbadminton.com/image/upload/v2/assets/flag-circle-svg-custom/ESP.png",
            "avatar": {
              "title": "Jacobo FERNANDEZ",
              "thumbnailUrl": "https://img.bwfbadminton.com/image/upload/assets/players/thumbnail/profile_male.jpg"
            }
          },
          {
            "id": "61331",
            "nameDisplay": "Alberto PERALS",
            "nameType": 0,
            "firstName": "Alberto",
            "lastName": "PERALS",
            "initials": "AP",
            "nameShort": "A PERALS",
            "nameShort2": "PERALS",
            "slug": "alberto-perals",
            "countryCode": "ESP",
            "countryName": null,
            "countryFlagUrl": "https://img.bwfbadminton.com/image/upload/v2/assets/flag-circle-svg-custom/ESP.png",
            "avatar": {
              "title": "Alberto PERALS",
              "thumbnailUrl": "https://img.bwfbadminton.com/image/upload/assets/players/thumbnail/profile_male.jpg"
            }
          }
        ],
        "linkName": null
      },
      "team2": {
        "countryCode": "IRL",
        "countryFlagUrl": "https://img.bwfbadminton.com/image/upload/v2/assets/flag-circle-svg-custom/IRL.png",
        "teamId": null,
        "teamName": null,
        "players": [
          {
            "id": "63756",
            "nameDisplay": "Scott GUILDEA",
            "nameType": 0,
            "firstName": "Scott",
            "lastName": "GUILDEA",
            "initials": "SG",
            "nameShort": "S GUILDEA",
            "nameShort2": "GUILDEA",
            "slug": "scott-guildea",
            "countryCode": "IRL",
            "countryName": null,
            "countryFlagUrl": "https://img.bwfbadminton.com/image/upload/v2/assets/flag-circle-svg-custom/IRL.png",
            "avatar": {
              "title": "Scott GUILDEA",
              "thumbnailUrl": "https://img.bwfbadminton.com/image/upload/assets/players/thumbnail/profile_male.jpg"
            }
          },
          {
            "id": "92985",
            "nameDisplay": "Paul REYNOLDS",
            "nameType": 0,
            "firstName": "Paul",
            "lastName": "REYNOLDS",
            "initials": "PR",
            "nameShort": "P REYNOLDS",
            "nameShort2": "REYNOLDS",
            "slug": "paul-reynolds",
            "countryCode": "IRL",
            "countryName": null,
            "countryFlagUrl": "https://img.bwfbadminton.com/image/upload/v2/assets/flag-circle-svg-custom/IRL.png",
            "avatar": {
              "title": "Paul REYNOLDS",
              "thumbnailUrl": "https://img.bwfbadminton.com/image/upload/v1604899249/assets/players/thumbnail/92985.jpg"
            }
          }
        ],
        "linkName": null
      },
      "team1seed": null,
      "team2seed": "2",
      "matchTime": "2025-10-28 10:25:00",
      "matchTimeUtc": "2025-10-28 09:25:00",
      "matchStatus": "F",
      "matchStatusValue": "Finished",
      "oopRound": "2",
      "oopText": "Followed by",
      "oopTypeId": 0,
      "eventName": "MD",
      "roundName": "Qual. QF",
      "drawName": "MD - Qualification",
      "drawCode": "5",
      "courtName": "Court 2",
      "courtCode": "2",
      "courtIndex": 1,
      "locationName": "Saarlandhalle",
      "duration": 31,
      "time": "00:31",
      "matchOrder": null,
      "matchTypeId": 3,
      "matchTypeValue": "Men's Doubles",
      "matchTypeNo": null,
      "reliability": 1,
      "score": [
        {
          "set": 1,
          "home": 21,
          "away": 14,
          "lastPointWinner": null,
          "serve": null
        },
        {
          "set": 2,
          "home": 21,
          "away": 18,
          "lastPointWinner": null,
          "serve": null
        }
      ],
      "matches": []
    }
  ],
  "drawsize": 4,
  "drawendcol": 4,
  "gameTypeId": 2
}